{
  "count": 15,
  "posts": [
    {
      "uuid": 1654686974761,
      "name": "dfvdfv",
      "done": false,
      "createdAt": 1654686974761
    },
    {
      "uuid": 1654686576255,
      "name": ",./k",
      "done": false,
      "createdAt": 1654686576255
    },
    {
      "uuid": 1654686569279,
      "name": "m,,",
      "done": false,
      "createdAt": 1654686569279
    },
    {
      "uuid": 1654686425689,
      "name": "dfgc",
      "done": false,
      "createdAt": 1654686425689
    },
    {
      "uuid": 1654686404049,
      "name": "dsf",
      "done": false,
      "createdAt": 1654686404049
    },
    {
      "uuid": 1654685241968,
      "name": "13",
      "done": false,
      "createdAt": 1654685241968
    },
    {
      "uuid": 1654684385215,
      "name": "8",
      "done": false,
      "createdAt": 1654684385215
    },
    {
      "uuid": 1654683339212,
      "name": "1",
      "done": false,
      "createdAt": 1654683339212
    },
    {
      "uuid": 1654611879409,
      "name": "1",
      "done": false,
      "createdAt": 1654611879409
    },
    {
      "uuid": 1654610127776,
      "name": "1",
      "done": false,
      "createdAt": 1654610127776
    },
    {
      "uuid": 1654610101160,
      "name": "1",
      "done": false,
      "createdAt": 1654610101160
    },
    {
      "uuid": 1654603222419,
      "name": "6",
      "done": false,
      "createdAt": 1654603222419
    },
    {
      "uuid": 1654603137196,
      "name": "5",
      "done": false,
      "createdAt": 1654603137196
    },
    {
      "uuid": 1654603132356,
      "name": "4",
      "done": false,
      "createdAt": 1654603132356
    },
    {
      "uuid": 1654602819424,
      "name": "2",
      "done": false,
      "createdAt": 1654602819424
    },
    {
      "uuid": 1654602640411,
      "name": "1",
      "done": false,
      "createdAt": 1654602640411
    },
    {
      "uuid": 1654683331268,
      "name": "1",
      "done": false,
      "createdAt": 1654683331268
    },
    {
      "uuid": 1654684373126,
      "name": "7",
      "done": false,
      "createdAt": 1654684373126
    },
    {
      "uuid": 1654686436488,
      "name": "dfv",
      "done": false,
      "createdAt": 1654686436488
    },
    {
      "uuid": 1654686510872,
      "name": "123",
      "done": false,
      "createdAt": 1654686510872
    },
    {
      "uuid": 1654686561215,
      "name": "sdf",
      "done": false,
      "createdAt": 1654686561215
    },
    {
      "uuid": 1654686666182,
      "name": "sdf",
      "done": false,
      "createdAt": 1654686666182
    },
    {
      "uuid": 1654686910290,
      "name": "23",
      "done": false,
      "createdAt": 1654686910290
    },
    {
      "uuid": 1654686983719,
      "name": "dfvdf",
      "done": false,
      "createdAt": 1654686983719
    },
    {
      "uuid": 1654687081615,
      "name": "1",
      "done": false,
      "createdAt": 1654687081615
    },
    {
      "uuid": 1654687083247,
      "name": "2",
      "done": false,
      "createdAt": 1654687083247
    },
    {
      "uuid": 1654687095599,
      "name": "13132",
      "done": false,
      "createdAt": 1654687095599
    }
  ]
}